MANIFEST.in
README.md
setup.py
Pyrametros.egg-info/PKG-INFO
Pyrametros.egg-info/SOURCES.txt
Pyrametros.egg-info/dependency_links.txt
Pyrametros.egg-info/top_level.txt
pyrametros/__init__.py
pyrametros/cfile.py
pyrametros/line.py
pyrametros/parser.py
pyrametros/examples/__init__.py
pyrametros/examples/opcode_gen.py
pyrametros/examples/source-control.py
pyrametros/test/__init__.py
pyrametros/test/common.py
pyrametros/test/test_cfile.py
pyrametros/test/test_line.py
pyrametros/test/test_parser.py