Metadata-Version: 1.1
Name: Pyrametros
Version: 0.9.5
Summary: A way to use ascii tables to automatically generate code.
Home-page: http://packages.python.org/Pyrmetros
Author: Chris Perivolaropoulos
Author-email: darksaga2006@gmail.com
License: GPL
Keywords: paramtetric source code table
Platform: UNKNOWN
Classifier: Programming Language :: Python :: 2.7
Classifier: License :: OSI Approved :: GNU General Public License v2 (GPLv2)
